drf_replace_ordering_filter/__init__.py
drf_replace_ordering_filter/filters.py
drf_replace_ordering_filter-1.0.1.dist-info/LICENSE
drf_replace_ordering_filter-1.0.1.dist-info/METADATA
drf_replace_ordering_filter-1.0.1.dist-info/WHEEL
drf_replace_ordering_filter-1.0.1.dist-info/top_level.txt
drf_replace_ordering_filter-1.0.1.dist-info/RECORD
