Metadata-Version: 2.1
Name: drf-replace-ordering-filter
Version: 1.0.1
Summary: Django Rest Framework OrderingFilter backend to replace field name in ordering params.
Home-page: https://github.com/emilsas/drf-replace-ordering-filter
Author: Emil Santurio
Author-email: emilsas@gmail.com
License: UNKNOWN
Platform: UNKNOWN
Classifier: Programming Language :: Python :: 3
Classifier: License :: OSI Approved :: MIT License
Classifier: Operating System :: OS Independent
Requires-Dist: djangorestframework
